ntpdatetime/__init__.py
ntpdatetime/config.py
ntpdatetime/ntpdatetime.py
ntpdatetime-0.1.7.dist-info/AUTHORS.rst
ntpdatetime-0.1.7.dist-info/LICENSE
ntpdatetime-0.1.7.dist-info/METADATA
ntpdatetime-0.1.7.dist-info/WHEEL
ntpdatetime-0.1.7.dist-info/top_level.txt
ntpdatetime-0.1.7.dist-info/RECORD
