Metadata-Version: 2.1
Name: ntpdatetime
Version: 0.1.7
Summary: Extend datetime module so it can return the time fetched from a NTP poolserver
Home-page: https://github.com/igroen/ntpdatetime
Author: Iwan in 't Groen
Author-email: iwanintgroen@gmail.com
License: ISCL
Keywords: ntpdatetime
Platform: UNKNOWN
Classifier: Development Status :: 2 - Pre-Alpha
Classifier: Intended Audience :: Developers
Classifier: License :: OSI Approved :: ISC License (ISCL)
Classifier: Natural Language :: English
Classifier: Programming Language :: Python :: 2
Classifier: Programming Language :: Python :: 2.6
Classifier: Programming Language :: Python :: 2.7
Classifier: Programming Language :: Python :: 3
Classifier: Programming Language :: Python :: 3.3
Classifier: Programming Language :: Python :: 3.4
Requires-Dist: ntplib
